TakeBlipInsightExtractor/__init__.py
TakeBlipInsightExtractor/insight_extractor.py
TakeBlipInsightExtractor/clustering/__init__.py
TakeBlipInsightExtractor/clustering/embedding.py
TakeBlipInsightExtractor/clustering/entity_cluster.py
TakeBlipInsightExtractor/inputs/__init__.py
TakeBlipInsightExtractor/inputs/file_validator.py
TakeBlipInsightExtractor/inputs/input_parameters.py
TakeBlipInsightExtractor/inputs/models_loader.py
TakeBlipInsightExtractor/outputs/__init__.py
TakeBlipInsightExtractor/outputs/api_response_message.py
TakeBlipInsightExtractor/outputs/email_sender.py
TakeBlipInsightExtractor/outputs/eventhub_log_sender.py
TakeBlipInsightExtractor/outputs/storage.py
TakeBlipInsightExtractor/processing/__init__.py
TakeBlipInsightExtractor/processing/entity_filter.py
TakeBlipInsightExtractor/registry/__init__.py
TakeBlipInsightExtractor/registry/azureml_logger.py
TakeBlipInsightExtractor/visualization/__init__.py
TakeBlipInsightExtractor/visualization/csv_file.py
TakeBlipInsightExtractor/visualization/entity_hierarchy.py
TakeBlipInsightExtractor/visualization/word_cloud.py
TakeBlipInsightExtractor-0.0.3.dist-info/METADATA
TakeBlipInsightExtractor-0.0.3.dist-info/WHEEL
TakeBlipInsightExtractor-0.0.3.dist-info/top_level.txt
TakeBlipInsightExtractor-0.0.3.dist-info/RECORD
