Metadata-Version: 2.1
Name: TakeBlipInsightExtractor
Version: 0.0.3
Summary: Insight Extractor Package
Home-page: UNKNOWN
Author: Data and Analytics Research
Author-email: analytics.dar@take.net
License: UNKNOWN
Keywords: insight extractor
Platform: UNKNOWN
Classifier: Programming Language :: Python :: 3
Classifier: License :: OSI Approved :: MIT License
Classifier: Operating System :: OS Independent
Requires-Dist: azure-eventhub
Requires-Dist: azure-storage-blob
Requires-Dist: wordcloud
Requires-Dist: matplotlib
Requires-Dist: numpy
Requires-Dist: scikit-learn
Requires-Dist: pyaap
Requires-Dist: gensim (==3.8.3)
Requires-Dist: TakeSentenceTokenizer (==1.0.1)
Requires-Dist: azureml-contrib-services
Requires-Dist: requests-toolbelt
